game_of_life_pyfection/board.py
game_of_life_pyfection/cell.py
game_of_life_pyfection/cli.py
game_of_life_pyfection/constants.py
game_of_life_pyfection/game.py
game_of_life_pyfection/settings.py
game_of_life_pyfection-0.1.0.dist-info/METADATA
game_of_life_pyfection-0.1.0.dist-info/RECORD
game_of_life_pyfection-0.1.0.dist-info/WHEEL
game_of_life_pyfection-0.1.0.dist-info/top_level.txt
