Metadata-Version: 2.1
Name: game-of-life-pyfection
Version: 0.1.0
Summary: Game of life: Pyfection
